{"0":{"country_name":"Afghanistan","totalAid_millions":"4064","totalAid_perCapita":"117","ISO":"AFG"},"1":{"country_name":"Albania","totalAid_millions":"169","totalAid_perCapita":"59","ISO":"ALB"},"2":{"country_name":"Algeria","totalAid_millions":"157","totalAid_perCapita":"4","ISO":"DZA"},"3":{"country_name":"American Samoa","totalAid_millions":"..","totalAid_perCapita":"..","ISO":"ASM"},"4":{"country_name":"Andorra","totalAid_millions":"..","totalAid_perCapita":"..","ISO":"AND"},"5":{"country_name":"Angola","totalAid_millions":"207","totalAid_perCapita":"7","ISO":"AGO"},"6":{"country_name":"Antigua and Barbuda","totalAid_millions":"0","totalAid_perCapita":"1","ISO":"ATG"},"7":{"country_name":"Argentina","totalAid_millions":"3","totalAid_perCapita":"0","ISO":"ARG"},"8":{"country_name":"Armenia","totalAid_millions":"327","totalAid_perCapita":"112","ISO":"ARM"},"9":{"country_name":"Aruba","totalAid_millions":"..","totalAid_perCapita":"..","ISO":"ABW"},"10":{"country_name":"Australia","totalAid_millions":"..","totalAid_perCapita":"..","ISO":"AUS"},"11":{"country_name":"Austria","totalAid_millions":"..","totalAid_perCapita":"..","ISO":"AUT"},"12":{"country_name":"Azerbaijan","totalAid_millions":"78","totalAid_perCapita":"8","ISO":"AZE"},"13":{"country_name":"Bahrain","totalAid_millions":"..","totalAid_perCapita":"..","ISO":"BHR"},"14":{"country_name":"Bangladesh","totalAid_millions":"2504","totalAid_perCapita":"15","ISO":"BGD"},"15":{"country_name":"Barbados","totalAid_millions":"..","totalAid_perCapita":"..","ISO":"BRB"},"16":{"country_name":"Belarus","totalAid_millions":"-22","totalAid_perCapita":"-2","ISO":"BLR"},"17":{"country_name":"Belgium","totalAid_millions":"..","totalAid_perCapita":"..","ISO":"BEL"},"18":{"country_name":"Belize","totalAid_millions":"35","totalAid_perCapita":"95","ISO":"BLZ"},"19":{"country_name":"Benin","totalAid_millions":"493","totalAid_perCapita":"45","ISO":"BEN"},"20":{"country_name":"Bermuda","totalAid_millions":"..","totalAid_perCapita":"..","ISO":"BMU"},"21":{"country_name":"Bhutan","totalAid_millions":"51","totalAid_perCapita":"65","ISO":"BTN"},"22":{"country_name":"Bosnia and Herzegovina","totalAid_millions":"445","totalAid_perCapita":"127","ISO":"BIH"},"23":{"country_name":"Botswana","totalAid_millions":"91","totalAid_perCapita":"40","ISO":"BWA"},"24":{"country_name":"Brazil","totalAid_millions":"675","totalAid_perCapita":"3","ISO":"BRA"},"25":{"country_name":"Brunei Darussalam","totalAid_millions":"..","totalAid_perCapita":"..","ISO":"BRN"},"26":{"country_name":"Bulgaria","totalAid_millions":"..","totalAid_perCapita":"..","ISO":"BGR"},"27":{"country_name":"Burkina Faso","totalAid_millions":"1023","totalAid_perCapita":"55","ISO":"BFA"},"28":{"country_name":"Burundi","totalAid_millions":"742","totalAid_perCapita":"71","ISO":"BDI"},"29":{"country_name":"Cabo Verde","totalAid_millions":"113","totalAid_perCapita":"210","ISO":"CPV"},"30":{"country_name":"Cambodia","totalAid_millions":"729","totalAid_perCapita":"46","ISO":"KHM"},"31":{"country_name":"Cameroon","totalAid_millions":"756","totalAid_perCapita":"32","ISO":"CMR"},"32":{"country_name":"Canada","totalAid_millions":"..","totalAid_perCapita":"..","ISO":"CAN"},"33":{"country_name":"Cayman Islands","totalAid_millions":"..","totalAid_perCapita":"..","ISO":"CYM"},"34":{"country_name":"Central African Republic","totalAid_millions":"500","totalAid_perCapita":"109","ISO":"CAF"},"35":{"country_name":"Chad","totalAid_millions":"624","totalAid_perCapita":"43","ISO":"TCD"},"36":{"country_name":"Chile","totalAid_millions":"178","totalAid_perCapita":"10","ISO":"CHL"},"37":{"country_name":"China","totalAid_millions":"-791","totalAid_perCapita":"-1","ISO":"CHN"},"38":{"country_name":"Colombia","totalAid_millions":"1107","totalAid_perCapita":"23","ISO":"COL"},"39":{"country_name":"Comoros","totalAid_millions":"55","totalAid_perCapita":"69","ISO":"COM"},"40":{"country_name":"Costa Rica","totalAid_millions":"101","totalAid_perCapita":"21","ISO":"CRI"},"41":{"country_name":"Croatia","totalAid_millions":"..","totalAid_perCapita":"..","ISO":"HRV"},"42":{"country_name":"Cuba","totalAid_millions":"2678","totalAid_perCapita":"233","ISO":"CUB"},"43":{"country_name":"Cyprus","totalAid_millions":"..","totalAid_perCapita":"..","ISO":"CYP"},"44":{"country_name":"Denmark","totalAid_millions":"..","totalAid_perCapita":"..","ISO":"DNK"},"45":{"country_name":"Djibouti","totalAid_millions":"185","totalAid_perCapita":"196","ISO":"DJI"},"46":{"country_name":"Dominica","totalAid_millions":"9","totalAid_perCapita":"116","ISO":"DMA"},"47":{"country_name":"Dominican Republic","totalAid_millions":"177","totalAid_perCapita":"17","ISO":"DOM"},"48":{"country_name":"Ecuador","totalAid_millions":"243","totalAid_perCapita":"15","ISO":"ECU"},"49":{"country_name":"El Salvador","totalAid_millions":"129","totalAid_perCapita":"20","ISO":"SLV"},"50":{"country_name":"Equatorial Guinea","totalAid_millions":"7","totalAid_perCapita":"6","ISO":"GNQ"},"51":{"country_name":"Eritrea","totalAid_millions":"67","totalAid_perCapita":"..","ISO":"ERI"},"52":{"country_name":"Estonia","totalAid_millions":"..","totalAid_perCapita":"..","ISO":"EST"},"53":{"country_name":"Ethiopia","totalAid_millions":"4074","totalAid_perCapita":"40","ISO":"ETH"},"54":{"country_name":"Faroe Islands","totalAid_millions":"..","totalAid_perCapita":"..","ISO":"FRO"},"55":{"country_name":"Fiji","totalAid_millions":"109","totalAid_perCapita":"121","ISO":"FJI"},"56":{"country_name":"Finland","totalAid_millions":"..","totalAid_perCapita":"..","ISO":"FIN"},"57":{"country_name":"France","totalAid_millions":"..","totalAid_perCapita":"..","ISO":"FRA"},"58":{"country_name":"French Polynesia","totalAid_millions":"..","totalAid_perCapita":"..","ISO":"PYF"},"59":{"country_name":"Gabon","totalAid_millions":"42","totalAid_perCapita":"21","ISO":"GAB"},"60":{"country_name":"Georgia","totalAid_millions":"463","totalAid_perCapita":"124","ISO":"GEO"},"61":{"country_name":"Germany","totalAid_millions":"..","totalAid_perCapita":"..","ISO":"DEU"},"62":{"country_name":"Ghana","totalAid_millions":"1316","totalAid_perCapita":"47","ISO":"GHA"},"63":{"country_name":"Greece","totalAid_millions":"..","totalAid_perCapita":"..","ISO":"GRC"},"64":{"country_name":"Greenland","totalAid_millions":"..","totalAid_perCapita":"..","ISO":"GRL"},"65":{"country_name":"Grenada","totalAid_millions":"9","totalAid_perCapita":"81","ISO":"GRD"},"66":{"country_name":"Guam","totalAid_millions":"..","totalAid_perCapita":"..","ISO":"GUM"},"67":{"country_name":"Guatemala","totalAid_millions":"266","totalAid_perCapita":"16","ISO":"GTM"},"68":{"country_name":"Guinea","totalAid_millions":"561","totalAid_perCapita":"45","ISO":"GIN"},"69":{"country_name":"Guinea-Bissau","totalAid_millions":"199","totalAid_perCapita":"110","ISO":"GNB"},"70":{"country_name":"Guyana","totalAid_millions":"70","totalAid_perCapita":"90","ISO":"GUY"},"71":{"country_name":"Haiti","totalAid_millions":"1074","totalAid_perCapita":"99","ISO":"HTI"},"72":{"country_name":"Honduras","totalAid_millions":"412","totalAid_perCapita":"45","ISO":"HND"},"73":{"country_name":"Hungary","totalAid_millions":"..","totalAid_perCapita":"..","ISO":"HUN"},"74":{"country_name":"Iceland","totalAid_millions":"..","totalAid_perCapita":"..","ISO":"ISL"},"75":{"country_name":"India","totalAid_millions":"2679","totalAid_perCapita":"2","ISO":"IND"},"76":{"country_name":"Indonesia","totalAid_millions":"-112","totalAid_perCapita":"0","ISO":"IDN"},"77":{"country_name":"Iraq","totalAid_millions":"2285","totalAid_perCapita":"61","ISO":"IRQ"},"78":{"country_name":"Ireland","totalAid_millions":"..","totalAid_perCapita":"..","ISO":"IRL"},"79":{"country_name":"Isle of Man","totalAid_millions":"..","totalAid_perCapita":"..","ISO":"IMN"},"80":{"country_name":"Israel","totalAid_millions":"..","totalAid_perCapita":"..","ISO":"ISR"},"81":{"country_name":"Italy","totalAid_millions":"..","totalAid_perCapita":"..","ISO":"ITA"},"82":{"country_name":"Jamaica","totalAid_millions":"27","totalAid_perCapita":"9","ISO":"JAM"},"83":{"country_name":"Japan","totalAid_millions":"..","totalAid_perCapita":"..","ISO":"JPN"},"84":{"country_name":"Jordan","totalAid_millions":"2739","totalAid_perCapita":"290","ISO":"JOR"},"85":{"country_name":"Kazakhstan","totalAid_millions":"61","totalAid_perCapita":"3","ISO":"KAZ"},"86":{"country_name":"Kenya","totalAid_millions":"2189","totalAid_perCapita":"45","ISO":"KEN"},"87":{"country_name":"Kiribati","totalAid_millions":"63","totalAid_perCapita":"553","ISO":"KIR"},"88":{"country_name":"Kuwait","totalAid_millions":"..","totalAid_perCapita":"..","ISO":"KWT"},"89":{"country_name":"Latvia","totalAid_millions":"..","totalAid_perCapita":"..","ISO":"LVA"},"90":{"country_name":"Lebanon","totalAid_millions":"1139","totalAid_perCapita":"190","ISO":"LBN"},"91":{"country_name":"Lesotho","totalAid_millions":"113","totalAid_perCapita":"51","ISO":"LSO"},"92":{"country_name":"Liberia","totalAid_millions":"815","totalAid_perCapita":"177","ISO":"LBR"},"93":{"country_name":"Libya","totalAid_millions":"179","totalAid_perCapita":"29","ISO":"LBY"},"94":{"country_name":"Liechtenstein","totalAid_millions":"..","totalAid_perCapita":"..","ISO":"LIE"},"95":{"country_name":"Lithuania","totalAid_millions":"..","totalAid_perCapita":"..","ISO":"LTU"},"96":{"country_name":"Luxembourg","totalAid_millions":"..","totalAid_perCapita":"..","ISO":"LUX"},"97":{"country_name":"Madagascar","totalAid_millions":"622","totalAid_perCapita":"25","ISO":"MDG"},"98":{"country_name":"Malawi","totalAid_millions":"1243","totalAid_perCapita":"69","ISO":"MWI"},"99":{"country_name":"Malaysia","totalAid_millions":"-52","totalAid_perCapita":"-2","ISO":"MYS"},"100":{"country_name":"Maldives","totalAid_millions":"27","totalAid_perCapita":"63","ISO":"MDV"},"101":{"country_name":"Mali","totalAid_millions":"1209","totalAid_perCapita":"67","ISO":"MLI"},"102":{"country_name":"Malta","totalAid_millions":"..","totalAid_perCapita":"..","ISO":"MLT"},"103":{"country_name":"Marshall Islands","totalAid_millions":"12","totalAid_perCapita":"233","ISO":"MHL"},"104":{"country_name":"Mauritania","totalAid_millions":"291","totalAid_perCapita":"68","ISO":"MRT"},"105":{"country_name":"Mauritius","totalAid_millions":"42","totalAid_perCapita":"34","ISO":"MUS"},"106":{"country_name":"Mexico","totalAid_millions":"809","totalAid_perCapita":"6","ISO":"MEX"},"107":{"country_name":"Monaco","totalAid_millions":"..","totalAid_perCapita":"..","ISO":"MCO"},"108":{"country_name":"Mongolia","totalAid_millions":"326","totalAid_perCapita":"108","ISO":"MNG"},"109":{"country_name":"Montenegro","totalAid_millions":"86","totalAid_perCapita":"138","ISO":"MNE"},"110":{"country_name":"Morocco","totalAid_millions":"1992","totalAid_perCapita":"56","ISO":"MAR"},"111":{"country_name":"Mozambique","totalAid_millions":"1531","totalAid_perCapita":"53","ISO":"MOZ"},"112":{"country_name":"Myanmar","totalAid_millions":"1534","totalAid_perCapita":"29","ISO":"MMR"},"113":{"country_name":"Namibia","totalAid_millions":"170","totalAid_perCapita":"69","ISO":"NAM"},"114":{"country_name":"Nepal","totalAid_millions":"1066","totalAid_perCapita":"37","ISO":"NPL"},"115":{"country_name":"Netherlands","totalAid_millions":"..","totalAid_perCapita":"..","ISO":"NLD"},"116":{"country_name":"New Caledonia","totalAid_millions":"..","totalAid_perCapita":"..","ISO":"NCL"},"117":{"country_name":"New Zealand","totalAid_millions":"..","totalAid_perCapita":"..","ISO":"NZL"},"118":{"country_name":"Nicaragua","totalAid_millions":"431","totalAid_perCapita":"70","ISO":"NIC"},"119":{"country_name":"Niger","totalAid_millions":"951","totalAid_perCapita":"46","ISO":"NER"},"120":{"country_name":"Nigeria","totalAid_millions":"2501","totalAid_perCapita":"13","ISO":"NGA"},"121":{"country_name":"Northern Mariana Islands","totalAid_millions":"..","totalAid_perCapita":"..","ISO":"MNP"},"122":{"country_name":"Norway","totalAid_millions":"..","totalAid_perCapita":"..","ISO":"NOR"},"123":{"country_name":"Oman","totalAid_millions":"..","totalAid_perCapita":"..","ISO":"OMN"},"124":{"country_name":"Pakistan","totalAid_millions":"2953","totalAid_perCapita":"15","ISO":"PAK"},"125":{"country_name":"Palau","totalAid_millions":"18","totalAid_perCapita":"823","ISO":"PLW"},"126":{"country_name":"Panama","totalAid_millions":"23","totalAid_perCapita":"6","ISO":"PAN"},"127":{"country_name":"Papua New Guinea","totalAid_millions":"528","totalAid_perCapita":"65","ISO":"PNG"},"128":{"country_name":"Paraguay","totalAid_millions":"89","totalAid_perCapita":"13","ISO":"PRY"},"129":{"country_name":"Peru","totalAid_millions":"320","totalAid_perCapita":"10","ISO":"PER"},"130":{"country_name":"Philippines","totalAid_millions":"287","totalAid_perCapita":"3","ISO":"PHL"},"131":{"country_name":"Poland","totalAid_millions":"..","totalAid_perCapita":"..","ISO":"POL"},"132":{"country_name":"Portugal","totalAid_millions":"..","totalAid_perCapita":"..","ISO":"PRT"},"133":{"country_name":"Puerto Rico","totalAid_millions":"..","totalAid_perCapita":"..","ISO":"PRI"},"134":{"country_name":"Qatar","totalAid_millions":"..","totalAid_perCapita":"..","ISO":"QAT"},"135":{"country_name":"Romania","totalAid_millions":"..","totalAid_perCapita":"..","ISO":"ROU"},"136":{"country_name":"Russian Federation","totalAid_millions":"..","totalAid_perCapita":"..","ISO":"RUS"},"137":{"country_name":"Rwanda","totalAid_millions":"1148","totalAid_perCapita":"96","ISO":"RWA"},"138":{"country_name":"Samoa","totalAid_millions":"88","totalAid_perCapita":"449","ISO":"WSM"},"139":{"country_name":"San Marino","totalAid_millions":"..","totalAid_perCapita":"..","ISO":"SMR"},"140":{"country_name":"Sao Tome and Principe","totalAid_millions":"47","totalAid_perCapita":"235","ISO":"STP"},"141":{"country_name":"Saudi Arabia","totalAid_millions":"..","totalAid_perCapita":"..","ISO":"SAU"},"142":{"country_name":"Senegal","totalAid_millions":"736","totalAid_perCapita":"48","ISO":"SEN"},"143":{"country_name":"Serbia","totalAid_millions":"633","totalAid_perCapita":"90","ISO":"SRB"},"144":{"country_name":"Seychelles","totalAid_millions":"6","totalAid_perCapita":"60","ISO":"SYC"},"145":{"country_name":"Sierra Leone","totalAid_millions":"693","totalAid_perCapita":"94","ISO":"SLE"},"146":{"country_name":"Singapore","totalAid_millions":"..","totalAid_perCapita":"..","ISO":"SGP"},"147":{"country_name":"Sint Maarten (Dutch part)","totalAid_millions":"..","totalAid_perCapita":"..","ISO":"SXM"},"148":{"country_name":"Slovenia","totalAid_millions":"..","totalAid_perCapita":"..","ISO":"SVN"},"149":{"country_name":"Solomon Islands","totalAid_millions":"182","totalAid_perCapita":"303","ISO":"SLB"},"150":{"country_name":"Somalia","totalAid_millions":"1169","totalAid_perCapita":"82","ISO":"SOM"},"151":{"country_name":"South Africa","totalAid_millions":"1181","totalAid_perCapita":"21","ISO":"ZAF"},"152":{"country_name":"South Sudan","totalAid_millions":"1590","totalAid_perCapita":"130","ISO":"SSD"},"153":{"country_name":"Spain","totalAid_millions":"..","totalAid_perCapita":"..","ISO":"ESP"},"154":{"country_name":"Sri Lanka","totalAid_millions":"365","totalAid_perCapita":"17","ISO":"LKA"},"155":{"country_name":"Sudan","totalAid_millions":"810","totalAid_perCapita":"..","ISO":"SDN"},"156":{"country_name":"Suriname","totalAid_millions":"17","totalAid_perCapita":"30","ISO":"SUR"},"157":{"country_name":"Eswatini","totalAid_millions":"147","totalAid_perCapita":"110","ISO":"SWZ"},"158":{"country_name":"Sweden","totalAid_millions":"..","totalAid_perCapita":"..","ISO":"SWE"},"159":{"country_name":"Switzerland","totalAid_millions":"..","totalAid_perCapita":"..","ISO":"CHE"},"160":{"country_name":"Syrian Arab Republic","totalAid_millions":"8870","totalAid_perCapita":"481","ISO":"SYR"},"161":{"country_name":"Tajikistan","totalAid_millions":"334","totalAid_perCapita":"38","ISO":"TJK"},"162":{"country_name":"Thailand","totalAid_millions":"228","totalAid_perCapita":"3","ISO":"THA"},"163":{"country_name":"Timor-Leste","totalAid_millions":"228","totalAid_perCapita":"179","ISO":"TLS"},"164":{"country_name":"Togo","totalAid_millions":"165","totalAid_perCapita":"22","ISO":"TGO"},"165":{"country_name":"Tonga","totalAid_millions":"80","totalAid_perCapita":"744","ISO":"TON"},"166":{"country_name":"Trinidad and Tobago","totalAid_millions":"..","totalAid_perCapita":"..","ISO":"TTO"},"167":{"country_name":"Tunisia","totalAid_millions":"627","totalAid_perCapita":"55","ISO":"TUN"},"168":{"country_name":"Turkey","totalAid_millions":"3613","totalAid_perCapita":"45","ISO":"TUR"},"169":{"country_name":"Turkmenistan","totalAid_millions":"33","totalAid_perCapita":"6","ISO":"TKM"},"170":{"country_name":"Turks and Caicos Islands","totalAid_millions":"..","totalAid_perCapita":"..","ISO":"TCA"},"171":{"country_name":"Tuvalu","totalAid_millions":"34","totalAid_perCapita":"3034","ISO":"TUV"},"172":{"country_name":"Uganda","totalAid_millions":"1757","totalAid_perCapita":"42","ISO":"UGA"},"173":{"country_name":"Ukraine","totalAid_millions":"1523","totalAid_perCapita":"34","ISO":"UKR"},"174":{"country_name":"United Arab Emirates","totalAid_millions":"..","totalAid_perCapita":"..","ISO":"ARE"},"175":{"country_name":"Uruguay","totalAid_millions":"18","totalAid_perCapita":"5","ISO":"URY"},"176":{"country_name":"Uzbekistan","totalAid_millions":"457","totalAid_perCapita":"14","ISO":"UZB"},"177":{"country_name":"Vanuatu","totalAid_millions":"129","totalAid_perCapita":"476","ISO":"VUT"},"178":{"country_name":"Virgin Islands (U.S.)","totalAid_millions":"..","totalAid_perCapita":"..","ISO":"VIR"},"179":{"country_name":"Zambia","totalAid_millions":"963","totalAid_perCapita":"58","ISO":"ZMB"},"180":{"country_name":"Zimbabwe","totalAid_millions":"655","totalAid_perCapita":"41","ISO":"ZWE"}}